degirum/CoreClient.cp312-win_amd64.pyd
degirum/LiberationMono-Regular.ttf
degirum/README.md
degirum/__init__.py
degirum/_draw_primitives.py
degirum/_filter_models.py
degirum/_misc.py
degirum/_model_param_helpers.py
degirum/_preprocessor.py
degirum/_socketio_msgpack.py
degirum/_tokens.py
degirum/_version.py
degirum/_zoo_accessor.py
degirum/aiclient.cp312-win_amd64.pyd
degirum/compiler.cp312-win_amd64.pyd
degirum/exceptions.py
degirum/hailo_runtime_agent--4.20.0.dgp
degirum/log.py
degirum/memryx_runtime_agent.dgp
degirum/model.py
degirum/model_params_dict.py
degirum/n2x_runtime_agent.dgp
degirum/onnx_runtime_agent.dgp
degirum/openvino_genai_runtime_agent--2025.3.0.dgp
degirum/openvino_runtime_agent--2023.3.0.dgp
degirum/openvino_runtime_agent--2024.6.0.dgp
degirum/openvino_runtime_agent--2025.3.0.dgp
degirum/pproc_worker.py
degirum/runtime_installer.py
degirum/server.py
degirum/tensorrt_runtime_agent.dgp
degirum/tflite_runtime_agent--205.dgp
degirum/tflite_runtime_agent--214.dgp
degirum/zoo_manager.py
degirum/FW/orca-1.1.fi
degirum/LICENSES/FP16/LICENSE
degirum/LICENSES/FXdiv/LICENSE
degirum/LICENSES/FreeRTOS/LICENSE.md
degirum/LICENSES/Source/LICENSE.md
degirum/LICENSES/abseil-cpp/LICENSE
degirum/LICENSES/asio/LICENSE_1_0.txt
degirum/LICENSES/benchmark/LICENSE
degirum/LICENSES/clog/LICENSE
degirum/LICENSES/compute_library/LICENSE
degirum/LICENSES/cpr/LICENSE
degirum/LICENSES/cpuinfo/LICENSE
degirum/LICENSES/crosstool/LICENSE
degirum/LICENSES/cuda/LICENSE
degirum/LICENSES/curl/LICENSE
degirum/LICENSES/dart/LICENSE
degirum/LICENSES/data/LICENSE
degirum/LICENSES/dotzlib/LICENSE_1_0.txt
degirum/LICENSES/eigen3/LICENSE
degirum/LICENSES/fft2d/LICENSE
degirum/LICENSES/flatbuffers/LICENSE
degirum/LICENSES/flatbuffers/LICENSE.txt
degirum/LICENSES/fmt/LICENSE.rst
degirum/LICENSES/gemmlowp/LICENSE
degirum/LICENSES/generator/LICENSE
degirum/LICENSES/googlemock/LICENSE
degirum/LICENSES/googletest/LICENSE
degirum/LICENSES/gtest/LICENSE
degirum/LICENSES/hadoop/LICENSE.txt
degirum-0.20.0.dist-info/LICENSE
degirum-0.20.0.dist-info/METADATA
degirum-0.20.0.dist-info/WHEEL
degirum-0.20.0.dist-info/entry_points.txt
degirum-0.20.0.dist-info/top_level.txt
degirum-0.20.0.dist-info/RECORD
